database_postgresql_local/__init__.py
database_postgresql_local/connector.py
database_postgresql_local/constants_src.py
database_postgresql_local/cursor.py
database_postgresql_local/generic_crud_postgresql.py
database_postgresql_local/table_columns.py
database_postgresql_local/table_definition.py
database_postgresql_local/utils.py
database_postgresql_local-0.1.2.1234.dist-info/METADATA
database_postgresql_local-0.1.2.1234.dist-info/WHEEL
database_postgresql_local-0.1.2.1234.dist-info/top_level.txt
database_postgresql_local-0.1.2.1234.dist-info/RECORD
