Metadata-Version: 2.4
Name: database-postgresql-local
Version: 0.1.2.1234
Summary: PyPI Package for Circles database-postgresql-local Python
Home-page: https://github.com/circles-zone/database-postgresql-local-python-package
Author: Circles
Author-email: info@circlez.ai
Classifier: Programming Language :: Python :: 3
Classifier: Operating System :: OS Independent
Requires-Dist: python-sdk-remote
Requires-Dist: logger-local
Requires-Dist: psycopg2
Dynamic: author
Dynamic: author-email
Dynamic: classifier
Dynamic: description
Dynamic: description-content-type
Dynamic: home-page
Dynamic: requires-dist
Dynamic: summary
